Metadata-Version: 1.0
Name: gaussdist100
Version: 0.1
Summary: Gaussian distributions
Home-page: https://github.com/Kenneth-Edwards
Author: Kenneth
Author-email: kenneth.nbt@gmail.com
License: UNKNOWN
Platform: UNKNOWN
